LICENSE
MANIFEST.in
README.rst
setup.cfg
setup.py
versioneer.py
artellapipe/__init__.py
artellapipe/tools/__init__.py
artellapipe/tools/artellauploader/__init__.py
artellapipe/tools/artellauploader/__logging__.ini
artellapipe/tools/artellauploader/__version__.py
artellapipe/tools/artellauploader/_version.py
artellapipe/tools/artellauploader/core/__init__.py
artellapipe/tools/artellauploader/core/artellauploader.py
artellapipe/tools/artellauploader/resources/icons/color/artella_upload.png
artellapipe/tools/artellauploader/resources/images/artellauploader_logo.png
artellapipe/tools/artellauploader/widgets/__init__.py
artellapipe/tools/artellauploader/widgets/artellauploadertool.py
artellapipe_tools_artellauploader.egg-info/PKG-INFO
artellapipe_tools_artellauploader.egg-info/SOURCES.txt
artellapipe_tools_artellauploader.egg-info/dependency_links.txt
artellapipe_tools_artellauploader.egg-info/not-zip-safe
artellapipe_tools_artellauploader.egg-info/requires.txt
artellapipe_tools_artellauploader.egg-info/top_level.txt
tests/__init__.py
tests/test_general.py