Metadata-Version: 2.1
Name: artellapipe-tools-artellauploader
Version: 0.0.7
Summary: Tool to easily upload files into Artella server
Home-page: https://github.com/ArtellaPipe/artellapipe-tools-artellauploader
Author: Tomas Poveda
Author-email: tpovedatd@gmail.com
License: MIT
Platform: UNKNOWN
Provides-Extra: test
Provides-Extra: dev
